github_commit_status/__init__.py
github_commit_status/cli.py
github_commit_status-1.4.0.dist-info/METADATA
github_commit_status-1.4.0.dist-info/WHEEL
github_commit_status-1.4.0.dist-info/entry_points.txt
github_commit_status-1.4.0.dist-info/licenses/LICENSE
github_commit_status-1.4.0.dist-info/RECORD
