Metadata-Version: 2.4
Name: github_commit_status
Version: 1.4.0
Summary: A simple command line for updating a commit's status on GitHub
Project-URL: Repository, https://github.com/glenjarvis/github_commit_status
Project-URL: Homepage, https://github.com/glenjarvis/github_commit_status
Author-email: Glen Jarvis <glen@glenjarvis.com>
License: MIT
License-File: LICENSE
Keywords: commit,git,github,github_commit_status
Requires-Python: >=3.10
Requires-Dist: click>=8.0
Requires-Dist: pygithub>=1.51
Requires-Dist: toml>=0.10
Provides-Extra: dev
Requires-Dist: black>=22.0; extra == 'dev'
Requires-Dist: coverage>=6.0; extra == 'dev'
Requires-Dist: mkdocs-material>=9.4; extra == 'dev'
Requires-Dist: mkdocs>=1.5; extra == 'dev'
Requires-Dist: mkdocstrings-python>=1.7; extra == 'dev'
Requires-Dist: pip-tools>=7.0; extra == 'dev'
Requires-Dist: pylint>=2.0; extra == 'dev'
Requires-Dist: pytest>5; extra == 'dev'
Requires-Dist: tox>=3.14; extra == 'dev'
Requires-Dist: twine>=4.0; extra == 'dev'
